BGCfinder/__init__.py
BGCfinder/__version__.py
BGCfinder/download.py
BGCfinder/main.py
BGCfinder/model.py
BGCfinder/utils.py
BGCfinder-0.0.30.dist-info/LICENSE.txt
BGCfinder-0.0.30.dist-info/METADATA
BGCfinder-0.0.30.dist-info/WHEEL
BGCfinder-0.0.30.dist-info/entry_points.txt
BGCfinder-0.0.30.dist-info/top_level.txt
BGCfinder-0.0.30.dist-info/RECORD
