Metadata-Version: 2.1
Name: BGCfinder
Version: 0.0.30
Summary: Biosynthetic Gene Cluster finder with Graph Neural Network
Home-page: https://github.com/jihunni/BGCfinder
Author: Jihun Jeung
Author-email: jihun@gm.gist.ac.kr
License: MIT
Keywords: Biosynthetic Gene Cluster
Classifier: Development Status :: 5 - Production/Stable
Classifier: Topic :: Scientific/Engineering
Classifier: Topic :: Scientific/Engineering :: Artificial Intelligence
Classifier: Topic :: Scientific/Engineering :: Bio-Informatics
Classifier: Topic :: Scientific/Engineering :: Chemistry
Requires-Python: >=3
License-File: LICENSE.txt
Requires-Dist: argparse
Requires-Dist: biopython (>=1.79)
Requires-Dist: rdkit-pypi (==2022.3.2.1)
Requires-Dist: pandas (==1.3.4)
Requires-Dist: numpy (==1.20.3)
Requires-Dist: appdirs (>=1.4.4)
